README.rst
setup.py
raypier/__init__.py
raypier/achromats.py
raypier/apertures.py
raypier/api.py
raypier/aspherics.py
raypier/bases.py
raypier/beamsplitters.py
raypier/beamstop.py
raypier/chirp_result.py
raypier/constraints.py
raypier/corner_cubes.py
raypier/decompositions.py
raypier/dielectrictroughs.py
raypier/diffraction_gratings.py
raypier/dispersion.py
raypier/distortions.py
raypier/editors.py
raypier/ellipsoids.py
raypier/faces.py
raypier/fields.py
raypier/gausslet_sources.py
raypier/general_optic.py
raypier/has_queue.py
raypier/intensity_image.py
raypier/intensity_surface.py
raypier/lenses.py
raypier/materials.py
raypier/mirrors.py
raypier/more_utils.py
raypier/parabolics.py
raypier/point_spread_func.py
raypier/prisms.py
raypier/probes.py
raypier/qt_future_call.py
raypier/results.py
raypier/shapes.py
raypier/sources.py
raypier/splines.py
raypier/step_export.py
raypier/tracer.py
raypier/utils.py
raypier/vtk_algorithms.py
raypier/waveplates.py
raypier/windows.py
raypier.egg-info/PKG-INFO
raypier.egg-info/SOURCES.txt
raypier.egg-info/dependency_links.txt
raypier.egg-info/not-zip-safe
raypier.egg-info/requires.txt
raypier.egg-info/top_level.txt
raypier/core/__init__.py
raypier/core/cdistortions.c
raypier/core/cdistortions.pyx
raypier/core/cfaces.c
raypier/core/cfaces.pyx
raypier/core/cfields.c
raypier/core/cfields.pyx
raypier/core/cmaterials.c
raypier/core/cmaterials.pyx
raypier/core/cshapes.c
raypier/core/cshapes.pyx
raypier/core/ctracer.c
raypier/core/ctracer.pxd
raypier/core/ctracer.pyx
raypier/core/fields.py
raypier/core/find_focus.py
raypier/core/gausslets.py
raypier/core/tracer.py
raypier/core/unwrap2d.py
raypier/core/utils.py
raypier/material_data/glass_dispersion_database.db
test/test_bezier.py
test/test_blank.py
test/test_broken_tvtk.py
test/test_cdistortions.py
test/test_cfaces.py
test/test_cmaterials.py
test/test_conic_lens.py
test/test_corner_cube.py
test/test_ctracer.py
test/test_delegation.py
test/test_ellipsoid.py
test/test_ellipsoid_export.py
test/test_extruded_interpolant.py
test/test_field_sources.py
test/test_fields.py
test/test_gaussian_ray_source.py
test/test_gausslet_collection.py
test/test_gratings.py
