Metadata-Version: 1.2
Name: raypier
Version: 0.2.2
Summary: A optical ray-tracing package, for design, optimisation and visualisation of mirror/lens systems.
Home-page: https://groups.google.com/u/1/g/python-raytrace
Author: Bryan Cole
Author-email: bryancole.cam@gmail.com
License: GPL3
Project-URL: Homepage, https://groups.google.com/u/1/g/python-raytrace
Project-URL: Documentation, https://raypier-optics.readthedocs.io/en/latest/index.html
Project-URL: Source, https://github.com/bryancole/raypier_optics.git
Project-URL: Issues, https://github.com/bryancole/raypier_optics/issues
Keywords: science engineering optics ray-tracing physcics
Platform: UNKNOWN
Classifier: Development Status :: 4 - Beta
Classifier: License :: OSI Approved :: GNU General Public License v3 (GPLv3)
Classifier: Natural Language :: English
Classifier: Programming Language :: Cython
Classifier: Programming Language :: Python :: 3.7
Classifier: Programming Language :: Python :: Implementation :: CPython
Classifier: Topic :: Scientific/Engineering :: Physics
Classifier: Topic :: Scientific/Engineering :: Visualization
Requires-Python: >=3.7
